{
  "$schema": "https://developer.microsoft.com/json-schemas/fabric/item/report/definition/visualContainer/2.5.0/schema.json",
  "name": "28fd5f01cbb9660fdaee",
  "position": {
    "x": 519.77229601518025,
    "y": 443.66856419987352,
    "z": 9000,
    "height": 260.69576217583807,
    "width": 364.32637571157494,
    "tabOrder": 9000
  },
  "visual": {
    "visualType": "lineChart",
    "query": {
      "queryState": {
        "Category": {
          "projections": [
            {
              "field": {
                "Column": {
                  "Expression": {
                    "SourceRef": {
                      "Entity": "agriculture-sylviculture-et-peche-valeur-ajoutee-de-croissance-annuelle-"
                    }
                  },
                  "Property": "date"
                }
              },
              "queryRef": "agriculture-sylviculture-et-peche-valeur-ajoutee-de-croissance-annuelle-.date",
              "nativeQueryRef": "date",
              "active": true
            }
          ]
        },
        "Y": {
          "projections": [
            {
              "field": {
                "Aggregation": {
                  "Expression": {
                    "Column": {
                      "Expression": {
                        "SourceRef": {
                          "Entity": "agriculture-sylviculture-et-peche-valeur-ajoutee-de-croissance-annuelle-"
                        }
                      },
                      "Property": "value"
                    }
                  },
                  "Function": 0
                }
              },
              "queryRef": "Sum(agriculture-sylviculture-et-peche-valeur-ajoutee-de-croissance-annuelle-.value)",
              "nativeQueryRef": "Somme de value"
            }
          ]
        }
      },
      "sortDefinition": {
        "sort": [
          {
            "field": {
              "Aggregation": {
                "Expression": {
                  "Column": {
                    "Expression": {
                      "SourceRef": {
                        "Entity": "agriculture-sylviculture-et-peche-valeur-ajoutee-de-croissance-annuelle-"
                      }
                    },
                    "Property": "value"
                  }
                },
                "Function": 0
              }
            },
            "direction": "Descending"
          }
        ],
        "isDefaultSort": true
      }
    },
    "objects": {
      "categoryAxis": [
        {
          "properties": {
            "bold": {
              "expr": {
                "Literal": {
                  "Value": "true"
                }
              }
            },
            "titleText": {
              "expr": {
                "Literal": {
                  "Value": "'Années'"
                }
              }
            },
            "titleBold": {
              "expr": {
                "Literal": {
                  "Value": "true"
                }
              }
            },
            "titleFontSize": {
              "expr": {
                "Literal": {
                  "Value": "12D"
                }
              }
            },
            "gridlineShow": {
              "expr": {
                "Literal": {
                  "Value": "false"
                }
              }
            }
          }
        }
      ],
      "valueAxis": [
        {
          "properties": {
            "gridlineShow": {
              "expr": {
                "Literal": {
                  "Value": "false"
                }
              }
            },
            "bold": {
              "expr": {
                "Literal": {
                  "Value": "true"
                }
              }
            },
            "titleText": {
              "expr": {
                "Literal": {
                  "Value": "'Contribution de l''agriculture à la croissance'"
                }
              }
            },
            "titleBold": {
              "expr": {
                "Literal": {
                  "Value": "true"
                }
              }
            },
            "titleFontSize": {
              "expr": {
                "Literal": {
                  "Value": "12D"
                }
              }
            }
          }
        }
      ],
      "dataPoint": [
        {
          "properties": {
            "fill": {
              "solid": {
                "color": {
                  "expr": {
                    "Literal": {
                      "Value": "'#e669b9'"
                    }
                  }
                }
              }
            }
          },
          "selector": {
            "metadata": "Sum(agriculture-sylviculture-et-peche-valeur-ajoutee-de-croissance-annuelle-.value)"
          }
        }
      ],
      "lineStyles": [
        {
          "properties": {
            "areaShow": {
              "expr": {
                "Literal": {
                  "Value": "true"
                }
              }
            }
          }
        }
      ]
    },
    "visualContainerObjects": {
      "dropShadow": [
        {
          "properties": {
            "show": {
              "expr": {
                "Literal": {
                  "Value": "true"
                }
              }
            }
          }
        }
      ],
      "background": [
        {
          "properties": {
            "color": {
              "solid": {
                "color": {
                  "expr": {
                    "Literal": {
                      "Value": "'#FF97D0'"
                    }
                  }
                }
              }
            },
            "transparency": {
              "expr": {
                "Literal": {
                  "Value": "100D"
                }
              }
            }
          }
        }
      ],
      "title": [
        {
          "properties": {
            "text": {
              "expr": {
                "Literal": {
                  "Value": "'Evolution de la part de l''agriculture dans la croissance annuelle'"
                }
              }
            },
            "bold": {
              "expr": {
                "Literal": {
                  "Value": "true"
                }
              }
            },
            "alignment": {
              "expr": {
                "Literal": {
                  "Value": "'center'"
                }
              }
            }
          }
        }
      ],
      "visualHeader": [
        {
          "properties": {
            "transparency": {
              "expr": {
                "Literal": {
                  "Value": "80D"
                }
              }
            }
          }
        }
      ]
    },
    "drillFilterOtherVisuals": true
  }
}